<?xml version='1.0' encoding='UTF-8'?><Response service="OrderService"><Head>OK</Head><Body><OrderResponse filter_result="2" destcode="755" mailno="SF7444400087417" origincode="755" orderid="SFKD-20160219000019"><rls_info rls_errormsg="SF7444400087417:" invoke_result="OK" rls_code="1000"><rls_detail waybillNo="SF7444400087417" sourceTransferCode="755W" sourceCityCode="755" sourceDeptCode="755AP" sourceTeamCode="028" destCityCode="755" destDeptCode="755FG" destDeptCodeMapping="755W" destTeamCode="016" destTransferCode="755W" destRouteLabel="755W-755FG" proName="顺丰标快" cargoTypeCode="C201" limitTypeCode="T4" expressTypeCode="B1" codingMapping="C2" xbFlag="0" printFlag="000000000" twoDimensionCode="MMM={'k1':'755W','k2':'755FG','k3':'016','k4':'T4','k5':'SF7444400087417','k6':'','k7':'33e4097c'}" proCode="T4" printIcon="00000000" checkCode="33e4097c"/></rls_info></OrderResponse></Body></Response>
